{"indexes":[{"v":{"$numberInt":"2"},"key":{"_id":{"$numberInt":"1"}},"name":"_id_"},{"v":{"$numberInt":"2"},"key":{"customer_name":{"$numberInt":"1"}},"name":"customer_name_1","background":true},{"v":{"$numberInt":"2"},"key":{"tag_type":{"$numberInt":"1"}},"name":"tag_type_1","background":true},{"v":{"$numberInt":"2"},"key":{"status":{"$numberInt":"1"}},"name":"status_1","background":true},{"v":{"$numberInt":"2"},"key":{"due_date":{"$numberInt":"1"}},"name":"due_date_1","background":true},{"v":{"$numberInt":"2"},"key":{"project_name":{"$numberInt":"1"}},"name":"project_name_1","background":true},{"v":{"$numberInt":"2"},"key":{"created_by":{"$numberInt":"1"}},"name":"created_by_1","background":true},{"v":{"$numberInt":"2"},"key":{"customer_name":{"$numberInt":"1"},"status":{"$numberInt":"1"}},"name":"customer_name_1_status_1","background":true},{"v":{"$numberInt":"2"},"key":{"tag_type":{"$numberInt":"1"},"status":{"$numberInt":"1"}},"name":"tag_type_1_status_1","background":true},{"v":{"$numberInt":"2"},"key":{"status":{"$numberInt":"1"},"due_date":{"$numberInt":"1"}},"name":"status_1_due_date_1","background":true},{"v":{"$numberInt":"2"},"key":{"items.item_id":{"$numberInt":"1"}},"name":"items.item_id_1","background":true},{"v":{"$numberInt":"2"},"key":{"createdAt":{"$numberInt":"-1"}},"name":"createdAt_-1","background":true},{"v":{"$numberInt":"2"},"key":{"_fts":"text","_ftsx":{"$numberInt":"1"}},"name":"customer_name_text_project_name_text_notes_text","background":true,"weights":{"customer_name":{"$numberInt":"1"},"notes":{"$numberInt":"1"},"project_name":{"$numberInt":"1"}},"default_language":"english","language_override":"language","textIndexVersion":{"$numberInt":"3"}},{"v":{"$numberInt":"2"},"key":{"customer_name":{"$numberInt":"1"},"tag_type":{"$numberInt":"1"},"status":{"$numberInt":"1"}},"name":"customer_name_1_tag_type_1_status_1","background":true},{"v":{"$numberInt":"2"},"key":{"tag_type":{"$numberInt":"1"},"status":{"$numberInt":"1"},"due_date":{"$numberInt":"1"}},"name":"tag_type_1_status_1_due_date_1","background":true}],"uuid":"c2fde35d20e14353a08a669b62167da1","collectionName":"tagnews","type":"collection"}